vectorvision/Converter.py
vectorvision/__init__.py
vectorvision/curve_optimization.py
vectorvision/main.py
vectorvision/path_decomposition.py
vectorvision/polygons.py
vectorvision/smoothing.py
vectorvision/utils.py
vectorvision/vertex_adjustment.py
vectorvision-0.1.2.dist-info/LICENSE
vectorvision-0.1.2.dist-info/METADATA
vectorvision-0.1.2.dist-info/WHEEL
vectorvision-0.1.2.dist-info/entry_points.txt
vectorvision-0.1.2.dist-info/RECORD
